metalarchivist/__init__.py
metalarchivist/export/__init__.py
metalarchivist/export/album.py
metalarchivist/export/band.py
metalarchivist/export/genre.py
metalarchivist/export/label.py
metalarchivist/export/util.py
metalarchivist/export/data/user-agents.json
metalarchivist/interface/__init__.py
metalarchivist/interface/album.py
metalarchivist/interface/band.py
metalarchivist/interface/genre.py
metalarchivist/interface/label.py
metalarchivist/interface/search.py
metalarchivist/interface/theme.py
metalarchivist/interface/api/base.py
metalarchivist/interface/api/page.py
test/test_albums.py
test/test_bands.py
test/test_genres.py
test/test_labels.py
test/test_themes.py
metalarchivist-0.6.4.dist-info/LICENSE
metalarchivist-0.6.4.dist-info/METADATA
metalarchivist-0.6.4.dist-info/WHEEL
metalarchivist-0.6.4.dist-info/top_level.txt
metalarchivist-0.6.4.dist-info/RECORD
