Metadata-Version: 2.1
Name: metalarchivist
Version: 0.6.4
Summary: A package for extracting data from metal-archives.com
Author-email: z3c0 <z3c0@21337.tech>
Project-URL: Homepage, https://gitlab.com/black-metal-book-club/metallum
Classifier: Programming Language :: Python :: 3
Classifier: License :: OSI Approved :: GNU Lesser General Public License v3 (LGPLv3)
Classifier: Operating System :: OS Independent
Requires-Python: >=3.11
License-File: LICENSE
Requires-Dist: lxml
Requires-Dist: urllib3
Requires-Dist: pycryptodome
